dagraph/__init__.py
dagraph/design.py
dagraph/interfaces/__init__.py
dagraph/interfaces/constraints.py
dagraph/interfaces/misc.py
dagraph/interfaces/model.py
dagraph/interfaces/optimizer.py
dagraph/interfaces/variables.py
dagraph/optimizers/__init__.py
dagraph/optimizers/slsqp.py
dagraph/optimizers/twiddle.py
dagraph-0.1.3.dist-info/METADATA
dagraph-0.1.3.dist-info/RECORD
dagraph-0.1.3.dist-info/WHEEL
dagraph-0.1.3.dist-info/top_level.txt
