Metadata-Version: 2.1
Name: dagraph
Version: 0.1.3
Summary: DAgraph - A directed acyclic graph generation library with integrated optimization
Home-page: UNKNOWN
Author: Rano Veder, Lorenzo Terenzi, Jose Ignacio de Alvear Cardenas
Author-email: UNKNOWN
License: MIT
Platform: UNKNOWN
